sensing_garden_client/__init__.py
sensing_garden_client/classifications.py
sensing_garden_client/client.py
sensing_garden_client/detections.py
sensing_garden_client/devices.py
sensing_garden_client/environment.py
sensing_garden_client/models.py
sensing_garden_client/shared.py
sensing_garden_client/videos.py
sensing_garden_client-0.0.14.post1.dist-info/LICENSE
sensing_garden_client-0.0.14.post1.dist-info/METADATA
sensing_garden_client-0.0.14.post1.dist-info/WHEEL
sensing_garden_client-0.0.14.post1.dist-info/RECORD
